lsst/__init__.py
lsst/ctrl/__init__.py
lsst/ctrl/mpexec/__init__.py
lsst/ctrl/mpexec/_pipeline_graph_factory.py
lsst/ctrl/mpexec/execFixupDataId.py
lsst/ctrl/mpexec/executionGraphFixup.py
lsst/ctrl/mpexec/log_capture.py
lsst/ctrl/mpexec/mpGraphExecutor.py
lsst/ctrl/mpexec/preExecInit.py
lsst/ctrl/mpexec/py.typed
lsst/ctrl/mpexec/quantumGraphExecutor.py
lsst/ctrl/mpexec/reports.py
lsst/ctrl/mpexec/separablePipelineExecutor.py
lsst/ctrl/mpexec/showInfo.py
lsst/ctrl/mpexec/simple_pipeline_executor.py
lsst/ctrl/mpexec/singleQuantumExecutor.py
lsst/ctrl/mpexec/taskFactory.py
lsst/ctrl/mpexec/util.py
lsst/ctrl/mpexec/version.py
lsst/ctrl/mpexec/cli/__init__.py
lsst/ctrl/mpexec/cli/butler_factory.py
lsst/ctrl/mpexec/cli/pipetask.py
lsst/ctrl/mpexec/cli/utils.py
lsst/ctrl/mpexec/cli/cmd/__init__.py
lsst/ctrl/mpexec/cli/cmd/commands.py
lsst/ctrl/mpexec/cli/opt/__init__.py
lsst/ctrl/mpexec/cli/opt/arguments.py
lsst/ctrl/mpexec/cli/opt/optionGroups.py
lsst/ctrl/mpexec/cli/opt/options.py
lsst/ctrl/mpexec/cli/script/__init__.py
lsst/ctrl/mpexec/cli/script/build.py
lsst/ctrl/mpexec/cli/script/cleanup.py
lsst/ctrl/mpexec/cli/script/confirmable.py
lsst/ctrl/mpexec/cli/script/pre_exec_init_qbb.py
lsst/ctrl/mpexec/cli/script/purge.py
lsst/ctrl/mpexec/cli/script/qgraph.py
lsst/ctrl/mpexec/cli/script/report.py
lsst/ctrl/mpexec/cli/script/run.py
lsst/ctrl/mpexec/cli/script/run_qbb.py
lsst/ctrl/mpexec/cli/script/update_graph_run.py
lsst_ctrl_mpexec-30.2026.400.dist-info/licenses/COPYRIGHT
lsst_ctrl_mpexec-30.2026.400.dist-info/licenses/LICENSE
lsst_ctrl_mpexec-30.2026.400.dist-info/licenses/bsd_license.txt
lsst_ctrl_mpexec-30.2026.400.dist-info/licenses/gpl-v3.0.txt
lsst_ctrl_mpexec-30.2026.400.dist-info/METADATA
lsst_ctrl_mpexec-30.2026.400.dist-info/WHEEL
lsst_ctrl_mpexec-30.2026.400.dist-info/entry_points.txt
lsst_ctrl_mpexec-30.2026.400.dist-info/top_level.txt
lsst_ctrl_mpexec-30.2026.400.dist-info/zip-safe
lsst_ctrl_mpexec-30.2026.400.dist-info/RECORD
