Metadata-Version: 2.4
Name: lsst-ctrl-mpexec
Version: 30.2026.400
Summary: Pipeline execution infrastructure for the Rubin Observatory LSST Science Pipelines.
Author-email: Rubin Observatory Data Management <dm-admin@lists.lsst.org>
License-Expression: BSD-3-Clause OR GPL-3.0-or-later
Project-URL: Homepage, https://github.com/lsst/ctrl_mpexec
Keywords: lsst
Classifier: Intended Audience :: Science/Research
Classifier: Operating System :: OS Independent
Classifier: Programming Language :: Python :: 3
Classifier: Programming Language :: Python :: 3.11
Classifier: Programming Language :: Python :: 3.12
Classifier: Programming Language :: Python :: 3.13
Classifier: Programming Language :: Python :: 3.14
Classifier: Topic :: Scientific/Engineering :: Astronomy
Requires-Python: >=3.11.0
License-File: COPYRIGHT
License-File: LICENSE
License-File: bsd_license.txt
License-File: gpl-v3.0.txt
Requires-Dist: lsst-utils
Requires-Dist: lsst-daf-butler
Requires-Dist: lsst-pex-config
Requires-Dist: lsst-pipe-base
Requires-Dist: click
Requires-Dist: astropy>=7.0
Requires-Dist: pydantic<3.0,>=2
Requires-Dist: networkx
Requires-Dist: psutil
Provides-Extra: coverage
Requires-Dist: coverage; extra == "coverage"
Provides-Extra: test
Requires-Dist: pytest>=3.2; extra == "test"
Dynamic: license-file
